{
  "cli": {
    "version": ">= 16.17.4",
    "appVersionSource": "remote"
  },
  "build": {
    "development": {
      "developmentClient": true,
      "distribution": "internal"
    },
    "development-sim": {
      "extends": "development",
      "ios": {
        "simulator": true
      }
    },
    "preview": {
      "distribution": "internal"
    },
    "production": {
      "autoIncrement": true,
      "node": "20.19.4",
      "ios": {
        "image": "macos-sequoia-15.6-xcode-26.2"
      }
    }
  },
  "submit": {
    "production": {
      "ios": {
        "ascAppId": "6761249131"
      }
    }
  }
}
